Metadata-Version: 1.0
Name: check-palindrome-PS1891
Version: 0.0.1
Summary: This is palindrome checking function
Home-page: UNKNOWN
Author: Prakash Shelar
Author-email: UNKNOWN
License: MIT
Keywords: palindrome,Python palindrome
Platform: UNKNOWN
